oremda/client/__init__.py
oremda/client/build/asset-manifest.json
oremda/client/build/favicon.ico
oremda/client/build/index.html
oremda/client/build/logo192.png
oremda/client/build/logo512.png
oremda/client/build/manifest.json
oremda/client/build/pipeline_1d.json
oremda/client/build/pipeline_2d.json
oremda/client/build/pipeline_peak.json
oremda/client/build/robots.txt
oremda/client/build/static/css/main.1ea371f6.chunk.css
oremda/client/build/static/css/main.1ea371f6.chunk.css.map
oremda/client/build/static/js/2.3843c2c2.chunk.js
oremda/client/build/static/js/2.3843c2c2.chunk.js.LICENSE.txt
oremda/client/build/static/js/2.3843c2c2.chunk.js.map
oremda/client/build/static/js/main.2ef556d3.chunk.js
oremda/client/build/static/js/main.2ef556d3.chunk.js.map
oremda/client/build/static/js/runtime-main.9c709cd5.js
oremda/client/build/static/js/runtime-main.9c709cd5.js.map
oremda_client-0.0.2.dist-info/WHEEL
oremda_client-0.0.2.dist-info/METADATA
oremda_client-0.0.2.dist-info/RECORD
