Metadata-Version: 2.1
Name: oremda-client
Version: 0.0.2
Summary: 
License: BSD-3-Clause
Author: Alessandro Genova
Author-email: alessandro.genova@kitware.com
Requires-Python: >=3.8,<4.0
Classifier: License :: OSI Approved :: BSD License
Classifier: Programming Language :: Python :: 3
Classifier: Programming Language :: Python :: 3.10
Classifier: Programming Language :: Python :: 3.8
Classifier: Programming Language :: Python :: 3.9
